README.txt
setup.py
birdcage/__init__.py
birdcage/example.py
birdcage/tests.py
birdcage.egg-info/PKG-INFO
birdcage.egg-info/SOURCES.txt
birdcage.egg-info/dependency_links.txt
birdcage.egg-info/entry_points.txt
birdcage.egg-info/top_level.txt
birdcage.egg-info/zip-safe