Metadata-Version: 1.1
Name: birdcage
Version: 0.9.0
Summary: library to squeeze text fragments into a phrase of a specified length.Used mainly to create tweets
Home-page: http://thesoftwarestudio.com/birdcage/
Author: Chris Davies
Author-email: user@domain.com
License: MIT
Platform: UNKNOWN
Classifier: Intended Audience :: Developers
Classifier: Programming Language :: Python
Classifier: License :: OSI Approved :: MIT License
